plonetheme.imioapps-2.55-py3.12-nspkg.pth
plonetheme/imioapps/__init__.py
plonetheme/imioapps/configure.zcml
plonetheme/imioapps/interfaces.py
plonetheme/imioapps/mk_sync_locales.sh
plonetheme/imioapps/profiles.zcml
plonetheme/imioapps/setuphandlers.py
plonetheme/imioapps/skins.zcml
plonetheme/imioapps/testing.py
plonetheme/imioapps/testing.zcml
plonetheme/imioapps/upgrades.py
plonetheme/imioapps/Extensions/Install.py
plonetheme/imioapps/Extensions/__init__.py
plonetheme/imioapps/browser/__init__.py
plonetheme/imioapps/browser/configure.zcml
plonetheme/imioapps/browser/overrides.py
plonetheme/imioapps/browser/viewlets.py
plonetheme/imioapps/browser/static/skin.js
plonetheme/imioapps/browser/templates/empty.pt
plonetheme/imioapps/browser/templates/help.pt
plonetheme/imioapps/browser/templates/viewlet_workflowstate.pt
plonetheme/imioapps/locales/eea.pot
plonetheme/imioapps/locales/plone.pot
plonetheme/imioapps/locales/en/LC_MESSAGES/eea.po
plonetheme/imioapps/locales/en/LC_MESSAGES/plone.po
plonetheme/imioapps/locales/fr/LC_MESSAGES/eea.po
plonetheme/imioapps/locales/fr/LC_MESSAGES/plone.po
plonetheme/imioapps/profiles/default/cssregistry.xml
plonetheme/imioapps/profiles/default/jsregistry.xml
plonetheme/imioapps/profiles/default/metadata.xml
plonetheme/imioapps/profiles/default/registry.xml
plonetheme/imioapps/profiles/default/skins.xml
plonetheme/imioapps/profiles/default/viewlets.xml
plonetheme/imioapps/profiles/dmsmailskin/cssregistry.xml
plonetheme/imioapps/profiles/dmsmailskin/dmsmailskin_marker.txt
plonetheme/imioapps/profiles/dmsmailskin/import_steps.xml
plonetheme/imioapps/profiles/dmsmailskin/metadata.xml
plonetheme/imioapps/profiles/dmsmailskin/skins.xml
plonetheme/imioapps/profiles/dmsmailskin/viewlets.xml
plonetheme/imioapps/profiles/plonemeetingskin/cssregistry.xml
plonetheme/imioapps/profiles/plonemeetingskin/import_steps.xml
plonetheme/imioapps/profiles/plonemeetingskin/metadata.xml
plonetheme_imioapps-2.55.dist-info/METADATA
plonetheme_imioapps-2.55.dist-info/WHEEL
plonetheme_imioapps-2.55.dist-info/entry_points.txt
plonetheme_imioapps-2.55.dist-info/namespace_packages.txt
plonetheme_imioapps-2.55.dist-info/top_level.txt
plonetheme_imioapps-2.55.dist-info/RECORD
