Metadata-Version: 2.4
Name: plonetheme.imioapps
Version: 2.55
Summary: Plone theme for most Imio applications
Home-page: https://github.com/IMIO/plonetheme.imioapps/
Author: IMIO team
Author-email: devs@imio.be
License: gpl
Keywords: Plone IMIO
Classifier: Development Status :: 6 - Mature
Classifier: Environment :: Web Environment
Classifier: Framework :: Plone
Classifier: License :: OSI Approved :: GNU General Public License (GPL)
Classifier: Operating System :: OS Independent
Classifier: Programming Language :: Python
Classifier: Programming Language :: Python :: 2.7
Classifier: Topic :: Software Development :: Libraries :: Python Modules
Requires-Dist: collective.fontawesome
Requires-Dist: collective.messagesviewlet
Requires-Dist: imio.helpers
Requires-Dist: setuptools
Provides-Extra: test
Requires-Dist: plone.app.testing; extra == "test"
Dynamic: author
Dynamic: author-email
Dynamic: classifier
Dynamic: description
Dynamic: home-page
Dynamic: keywords
Dynamic: license
Dynamic: provides-extra
Dynamic: requires-dist
Dynamic: summary
